flask_nova/__init__.py
flask_nova/cli.py
flask_nova/core.py
flask_nova/di.py
flask_nova/docs/__init__.py
flask_nova/docs/docs.py
flask_nova/docs/openapi.py
flask_nova/exceptions.py
flask_nova/logger.py
flask_nova/multi_part.py
flask_nova/responses.py
flask_nova/route_refactor.py
flask_nova/router.py
flask_nova/scripts/__ini__.py
flask_nova/scripts/typecheck.py
flask_nova/status.py
flask_nova/types.py
flask_nova/utils.py
flask_nova-0.1.2.dist-info/entry_points.txt
flask_nova-0.1.2.dist-info/LICENSE
flask_nova-0.1.2.dist-info/METADATA
flask_nova-0.1.2.dist-info/WHEEL
flask_nova-0.1.2.dist-info/RECORD
