Metadata-Version: 2.3
Name: flask-nova
Version: 0.1.2
Summary: Extra check using pydandic in flask application
License: MIT
Author: manitreasure1
Author-email: manitreasure1@gmail.com
Requires-Python: >=3.10
Classifier: License :: OSI Approved :: MIT License
Classifier: Programming Language :: Python :: 3
Classifier: Programming Language :: Python :: 3.10
Classifier: Programming Language :: Python :: 3.11
Classifier: Programming Language :: Python :: 3.12
Classifier: Programming Language :: Python :: 3.13
Requires-Dist: flask[async] (>=3.1.1,<4.0.0)
Requires-Dist: pydantic (>=2.11.7,<3.0.0)
